python_http_client-stubs/METADATA.toml
python_http_client-stubs/__init__.pyi
python_http_client-stubs/client.pyi
python_http_client-stubs/exceptions.pyi
python_http_client-stubs/py.typed
types_python_http_client-3.3.7.20240910.dist-info/METADATA
types_python_http_client-3.3.7.20240910.dist-info/WHEEL
types_python_http_client-3.3.7.20240910.dist-info/top_level.txt
types_python_http_client-3.3.7.20240910.dist-info/RECORD
